{
  "system_name": "REC.IO Trading System",
  "created": "2025-08-09",
  "updated": "2025-01-27",
  "description": "MASTER PORT MANIFEST - Single source of truth for ALL port assignments",
  
  "core_services": {
    "main_app": {
      "port": 3000,
      "description": "Main web application with enhanced system monitoring",
      "status": "RUNNING"
    },
    "trade_manager": {
      "port": 4000,
      "description": "Trade management service",
      "status": "RUNNING"
    },
    "trade_executor": {
      "port": 5000,
      "description": "Trade execution service",
      "status": "RUNNING"
    },
    "active_trade_supervisor": {
      "port": 8007,
      "description": "Active trade monitoring",
      "status": "RUNNING"
    },
    "auto_entry_supervisor": {
      "port": 8008,
      "description": "Auto entry monitoring and indicators",
      "status": "RUNNING"
    }
  },
  
  "watchdog_services": {
    "symbol_price_watchdog_btc": {
      "port": 8014,
      "description": "BTC symbol price monitoring with PostgreSQL storage",
      "status": "RUNNING"
    },
    "symbol_price_watchdog_eth": {
      "port": 8015,
      "description": "ETH symbol price monitoring with PostgreSQL storage",
      "status": "RUNNING"
    },
    "kalshi_account_sync": {
      "port": 8012,
      "description": "Kalshi account synchronization",
      "status": "RUNNING"
    },
    "kalshi_api_watchdog": {
      "port": 8013,
      "description": "Kalshi API monitoring",
      "status": "RUNNING"
    },
    "unified_production_coordinator": {
      "port": 8010,
      "description": "Unified data production coordinator",
      "status": "RUNNING"
    },
    "cascading_failure_detector": {
      "port": 8009,
      "description": "Cascading failure detection and prevention",
      "status": "RUNNING"
    },
    "system_monitor": {
      "port": 8011,
      "description": "Comprehensive system health monitoring with duplicate process detection",
      "status": "RUNNING"
    }
  },
  
  "deprecated_services": {
    "btc_price_watchdog": {
      "port": 8002,
      "description": "Bitcoin price monitoring (DEPRECATED - Migrated to PostgreSQL)",
      "status": "ARCHIVED",
      "archive_location": "archive/deprecated_services/",
      "replacement": "symbol_price_watchdog_btc"
    }
  },
  
  "port_ranges": {
    "safe_range_start": 8000,
    "safe_range_end": 8100,
    "description": "Safe port range avoiding macOS system services"
  },
  
  "notes": {
    "avoid_ports": [5000, 7000, 9000, 10000],
    "reason": "These ports conflict with macOS AirPlay, ControlCenter, and other system services",
    "frontend_enhancements": "Enhanced system monitoring and admin controls implemented",
    "mobile_interface": "Mobile-optimized interface available",
    "duplicate_process_detection": "System monitor includes duplicate process detection and cleanup",
    "postgresql_migration": "All services migrated to PostgreSQL data architecture",
    "deprecated_services": "btc_price_watchdog and live_data_analysis.py archived",
    "data_architecture": "Centralized PostgreSQL live_data schema for all market data"
  }
} 